datastream/__init__.py
datastream/dataset.py
datastream/datastream.py
datastream/samplers/__init__.py
datastream/samplers/merge_sampler.py
datastream/samplers/multi_sampler.py
datastream/samplers/repeat_sampler.py
datastream/samplers/sequential_sampler.py
datastream/samplers/standard_sampler.py
datastream/samplers/zip_sampler.py
datastream/tools/__init__.py
datastream/tools/numpy_seed.py
datastream/tools/repeat_map_chain.py
datastream/tools/split_dataframes.py
datastream/tools/star.py
datastream/tools/starcompose.py
datastream/tools/stratified_split.py
datastream/tools/unstratified_split.py
datastream/tools/verify_split.py
pytorch_datastream-0.4.12.dist-info/LICENSE
pytorch_datastream-0.4.12.dist-info/WHEEL
pytorch_datastream-0.4.12.dist-info/METADATA
pytorch_datastream-0.4.12.dist-info/RECORD
