Metadata-Version: 2.1
Name: pytorch-datastream
Version: 0.4.12
Summary: Simple dataset to dataloader library for pytorch
Home-page: https://github.com/nextml-code/pytorch-datastream
License: Apache-2.0
Keywords: pytorch,machine,learning,dataset,pipeline,dataloader
Author: NextML
Requires-Python: >=3.8,<4.0
Classifier: Development Status :: 3 - Alpha
Classifier: Environment :: Other Environment
Classifier: Intended Audience :: Developers
Classifier: Intended Audience :: Science/Research
Classifier: License :: OSI Approved :: Apache Software License
Classifier: Operating System :: OS Independent
Classifier: Programming Language :: Python :: 3
Classifier: Programming Language :: Python :: 3.8
Classifier: Programming Language :: Python :: 3.9
Classifier: Programming Language :: Python :: 3.10
Classifier: Programming Language :: Python :: 3.11
Classifier: Topic :: Scientific/Engineering
Classifier: Topic :: Scientific/Engineering :: Artificial Intelligence
Classifier: Topic :: Software Development
Classifier: Topic :: Software Development :: Libraries
Classifier: Topic :: Software Development :: Libraries :: Python Modules
Requires-Dist: numpy (>=1.17.0,<2.0.0)
Requires-Dist: pandas (>=1.0.5,<2.0.0)
Requires-Dist: pydantic (>=2.0.0,<3.0.0)
Requires-Dist: torch (>=1.4.0)
Project-URL: Documentation, https://pytorch-datastream.readthedocs.io
Project-URL: Repository, https://github.com/nextml-code/pytorch-datastream
